stock_tools/__init__.py
stock_tools/adjust_price.py
stock_tools/emulate_trade.py
stock_tools/exceptions.py
stock_tools/fetch.py
stock_tools/key.py
stock_tools/monkey_investor.py
stock_tools/price_cache.py
stock_tools/stock_statistics.py
stock_tools/transaction_and_state.py
stock_tools-0.1.1.dist-info/LICENSE
stock_tools-0.1.1.dist-info/METADATA
stock_tools-0.1.1.dist-info/WHEEL
stock_tools-0.1.1.dist-info/RECORD
