Metadata-Version: 2.1
Name: stock-tools
Version: 0.1.1
Summary: 알고리즘 주식 투자를 위한 여러 툴을 모아놓은 라이브러리입니다.
License: MIT
Author: ilotoki0804
Author-email: ilotoki0804@gmail.com
Requires-Python: >=3.11.0,<3.12.0
Classifier: License :: OSI Approved :: MIT License
Classifier: Programming Language :: Python :: 3
Classifier: Programming Language :: Python :: 3.11
Requires-Dist: matplotlib (>=3.8.2,<4.0.0)
Requires-Dist: mojito2 (>=0.1.6,<0.2.0)
Requires-Dist: numpy (>=1.26.2,<2.0.0)
Requires-Dist: pandas (>=2.1.3,<3.0.0)
Requires-Dist: python-kis (>=1.0.6,<2.0.0)
